neos_common/__init__.py
neos_common/api.py
neos_common/base.py
neos_common/changelog.py
neos_common/cli.py
neos_common/config.py
neos_common/error.py
neos_common/event.py
neos_common/schema.py
neos_common/util.py
neos_common/authorization/__init__.py
neos_common/authorization/base.py
neos_common/authorization/token.py
neos_common/authorization/util.py
neos_common/authorization/validator.py
neos_common/client/__init__.py
neos_common/client/base.py
neos_common/client/email.py
neos_common/client/hub_client.py
neos_common/client/kafka_client.py
neos_common/client/keycloak_client.py
neos_common/middleware/__init__.py
neos_common/middleware/timing.py
neos_common/socket/__init__.py
neos_common/socket/client.py
neos_common/socket/server.py
neos_common/socket/util.py
neos_common-0.14.17.dist-info/METADATA
neos_common-0.14.17.dist-info/WHEEL
neos_common-0.14.17.dist-info/RECORD
