Metadata-Version: 2.3
Name: neos_common
Version: 0.14.17
Summary: Neos Common Code
Requires-Python: >=3.10
Requires-Dist: auth-aws4>=0.1.1
Requires-Dist: httpx
Requires-Dist: jinja2>=3
Requires-Dist: multidict>=6.0.0
Requires-Dist: pdoc3>=0.11.1
Requires-Dist: pydantic>=2.0.0
Requires-Dist: python-dotenv
Provides-Extra: auth
Requires-Dist: fastapi<1.0.0,>=0.0.0; extra == 'auth'
Requires-Dist: python-keycloak<4.0,>=3.9; extra == 'auth'
Provides-Extra: config
Requires-Dist: pydantic-settings<3.0.0,>=2.0.0; extra == 'config'
Provides-Extra: dev
Requires-Dist: changelog-gen<0.13,>=0.12; extra == 'dev'
Requires-Dist: freezegun>=1.2.1; extra == 'dev'
Requires-Dist: pre-commit>=3.7.1; extra == 'dev'
Requires-Dist: pytest-asyncio<0.19,>=0.18.3; extra == 'dev'
Requires-Dist: pytest-cov>=3.0.0; extra == 'dev'
Requires-Dist: pytest-env>=0.6.2; extra == 'dev'
Requires-Dist: pytest-httpx; extra == 'dev'
Requires-Dist: pytest-random-order>=1.0.4; extra == 'dev'
Requires-Dist: pytest<8.0,>=7.1.2; extra == 'dev'
Requires-Dist: ruff>=0.6.4; extra == 'dev'
Provides-Extra: kafka
Requires-Dist: confluent-kafka==2.0.2; extra == 'kafka'
